{
    "id": "ryuko-matoi",
    "title": "Ryuko Matoi",
    "description": "Ryuko Matoi comic.",
    "author": "DarkensHorns",
    "status": "Ongoing",
    "cover": "https://ah-img.luscious.net/darkenshorns/618164/1_01KXEB1MP5H0T6BDY6RJCD4G19.1280x0.jpg",
    "banner": "https://ah-img.luscious.net/darkenshorns/618164/3b_01KXEB1RZJ91XWFQMSX3P51JT0.1280x0.jpg",
    "rating": "5.0",
    "updated": "2026-07-21",
    "genres": [
        "Action",
        "Fantasy",
        "Adult"
    ],
    "tags": [
        "Ryuko Matoi",
        "Dark",
        "AI"
    ],
    "characters": [
        "Ryuko Matoi"
    ],
    "chapters": [
        {
            "id": "Chapter-01",
            "title": "Chapter 01",
            "folder": "Ryuko-vs-Huge-Dildo"
        }
    ]
}
